[{"domain":null,"method":"GET|HEAD","uri":"\/","name":null,"action":"Closure","middleware":["web"]},{"domain":null,"method":"POST","uri":"_ignition\/execute-solution","name":"ignition.executeSolution","action":"Spatie\\LaravelIgnition\\Http\\Controllers\\ExecuteSolutionController","middleware":["Spatie\\LaravelIgnition\\Http\\Middleware\\RunnableSolutionsEnabled"]},{"domain":null,"method":"GET|HEAD","uri":"_ignition\/health-check","name":"ignition.healthCheck","action":"Spatie\\LaravelIgnition\\Http\\Controllers\\HealthCheckController","middleware":["Spatie\\LaravelIgnition\\Http\\Middleware\\RunnableSolutionsEnabled"]},{"domain":null,"method":"POST","uri":"_ignition\/update-config","name":"ignition.updateConfig","action":"Spatie\\LaravelIgnition\\Http\\Controllers\\UpdateConfigController","middleware":["Spatie\\LaravelIgnition\\Http\\Middleware\\RunnableSolutionsEnabled"]},{"domain":null,"method":"GET|HEAD","uri":"api\/contact","name":"contact","action":"App\\Http\\Controllers\\ContactController@contact","middleware":["api"]},{"domain":null,"method":"POST","uri":"api\/contact-member","name":"admin-contactmember","action":"App\\Http\\Controllers\\ContactController@contactmember","middleware":["api"]},{"domain":null,"method":"GET|HEAD","uri":"api\/contact-message\/{id}","name":"contacts","action":"App\\Http\\Controllers\\ContactController@contacts","middleware":["api"]},{"domain":null,"method":"GET|HEAD","uri":"api\/dashboard","name":"dashboard","action":"App\\Http\\Controllers\\Auth\\UserController@dashboard","middleware":["api","App\\Http\\Middleware\\Authenticate:api"]},{"domain":null,"method":"POST","uri":"api\/login","name":"user-login","action":"App\\Http\\Controllers\\Auth\\UserController@login","middleware":["api"]},{"domain":null,"method":"POST","uri":"api\/logout","name":"user-logout","action":"App\\Http\\Controllers\\Auth\\UserController@logout","middleware":["api","App\\Http\\Middleware\\Authenticate:api"]},{"domain":null,"method":"POST","uri":"api\/register","name":"user-register","action":"App\\Http\\Controllers\\Auth\\UserController@register","middleware":["api"]},{"domain":null,"method":"GET|HEAD","uri":"api\/user","name":null,"action":"Closure","middleware":["api","App\\Http\\Middleware\\Authenticate:sanctum"]},{"domain":null,"method":"GET|HEAD","uri":"api\/user-delete\/{id}","name":"admin-user-delete","action":"App\\Http\\Controllers\\Auth\\UserController@userDelete","middleware":["api","App\\Http\\Middleware\\Authenticate:api"]},{"domain":null,"method":"GET|HEAD","uri":"api\/user-update\/{id}","name":"admin-user-update","action":"App\\Http\\Controllers\\Auth\\UserController@userUpdate","middleware":["api","App\\Http\\Middleware\\Authenticate:api"]},{"domain":null,"method":"POST","uri":"api\/user-updated","name":"admin-user-updated","action":"App\\Http\\Controllers\\Auth\\UserController@userUpdated","middleware":["api","App\\Http\\Middleware\\Authenticate:api"]},{"domain":null,"method":"GET|HEAD","uri":"api\/users","name":"admin-users","action":"App\\Http\\Controllers\\Auth\\UserController@users","middleware":["api","App\\Http\\Middleware\\Authenticate:api"]},{"domain":null,"method":"GET|HEAD","uri":"sanctum\/csrf-cookie","name":"sanctum.csrf-cookie","action":"Laravel\\Sanctum\\Http\\Controllers\\CsrfCookieController@show","middleware":["web"]}]
